{"type":"FeatureCollection","features":[{"type":"Feature","geometry":{"type":"Point","name":"Teste","coordinates":[-47.498324,-4.950893]}},{"type":"Feature","geometry":{"type":"Point","coordinates":[-42.825697,-2.751912]}},{"type":"Feature","geometry":{"type":"Point","coordinates":[-46.035877,-7.528608]}},{"type":"Feature","geometry":{"type":"Point","coordinates":[-44.778464,-4.232571]}},{"type":"Feature","geometry":{"type":"Point","coordinates":[-45.23861,-5.50959]}},{"type":"Feature","geometry":{"type":"Point","coordinates":[-44.869016,-1.82639]}},{"type":"Feature","geometry":{"type":"Point","coordinates":[-43.364634,-4.863498]}},{"type":"Feature","geometry":{"type":"Point","coordinates":[-43.885386,-4.453502]}},{"type":"Feature","geometry":{"type":"Point","coordinates":[-44.123854,-4.129178]}},{"type":"Feature","geometry":{"type":"Point","coordinates":[-43.363652,-3.741063]}},{"type":"Feature","geometry":{"type":"Point","coordinates":[-47.471329,-7.333788]}},{"type":"Feature","geometry":{"type":"Point","coordinates":[-47.439855,-6.563893]}},{"type":"Feature","geometry":{"type":"Point","coordinates":[-44.229276,-2.560852]}},{"type":"Feature","geometry":{"type":"Point","coordinates":[-44.296282,-2.526333]}},{"type":"Feature","geometry":{"type":"Point","coordinates":[-44.358492,-3.392057]}},{"type":"Feature","geometry":{"type":"Point","coordinates":[-47.469531,-5.528767]}},{"type":"Feature","geometry":{"type":"Point","coordinates":[-44.602508,-4.570876]}},{"type":"Feature","geometry":{"type":"Point","coordinates":[-44.492649,-5.283024]}},{"type":"Feature","geometry":{"type":"Point","coordinates":[-45.086454,-2.519427]}},{"type":"Feature","geometry":{"type":"Point","coordinates":[-44.191649,-2.55139]}},{"type":"Feature","geometry":{"type":"Point","coordinates":[-44.303139,-2.508644]}},{"type":"Feature","geometry":{"type":"Point","coordinates":[-45.377392,-3.656292]}},{"type":"Feature","geometry":{"type":"Point","coordinates":[-44.072544,-2.551021]}},{"type":"Feature","geometry":{"type":"Point","coordinates":[-43.704425,-6.493722]}},{"type":"Feature","geometry":{"type":"Point","coordinates":[-45.656769,-3.969481]}},{"type":"Feature","geometry":{"type":"Point","coordinates":[-44.255105,-2.527161]}},{"type":"Feature","geometry":{"type":"Point","coordinates":[-42.822149,-5.098353]}},{"type":"Feature","geometry":{"type":"Point","coordinates":[-44.286843,-2.499301]}},{"type":"Feature","geometry":{"type":"Point","coordinates":[-45.002082,-3.217373]}},{"type":"Feature","geometry":{"type":"Point","coordinates":[-44.305321,-2.52589]}}]}